<?xml version="1.1" encoding="UTF-8" standalone="no"?>
<databaseChangeLog xmlns="http://www.liquibase.org/xml/ns/dbchangelog" xmlns:xsi="http://www.w3.org/2001/XMLSchema-instance"
                   xsi:schemaLocation="http://www.liquibase.org/xml/ns/dbchangelog http://www.liquibase.org/xml/ns/dbchangelog/dbchangelog-3.8.xsd">

    <changeSet id="2021-11-04--01--init-db-schema.xml" author="BKezikov">
        <createTable tableName="cars">
            <column name="id" type="UUID" defaultValueComputed="${uuid_function}">
                <constraints nullable="false" primaryKey="true"/>
            </column>
            <column name="color" type="VARCHAR(10)">
                <constraints nullable="false"/>
            </column>
            <column name="model" type="VARCHAR(50)">
                <constraints nullable="false"/>
            </column>
            <column name="number" type="VARCHAR(40)">
                <constraints nullable="false"/>
            </column>
            <column name="car_class" type="VARCHAR(15)">
                <constraints nullable="false"/>
            </column>
            <column name="created_at" type="TIMESTAMP">
                <constraints nullable="false"/>
            </column>
            <column name="updated_at" type="TIMESTAMP">
                <constraints nullable="false"/>
            </column>
        </createTable>

    </changeSet>
</databaseChangeLog>